Deepfry/__init__.py
Deepfry/deepfry.py
Deepfry-1.0.0.dist-info/LICENSE.txt
Deepfry-1.0.0.dist-info/METADATA
Deepfry-1.0.0.dist-info/WHEEL
Deepfry-1.0.0.dist-info/top_level.txt
Deepfry-1.0.0.dist-info/RECORD
